tasks_library/__init__.py
tasks_library/processor.py
tasks_library-0.1.0.dist-info/METADATA
tasks_library-0.1.0.dist-info/WHEEL
tasks_library-0.1.0.dist-info/top_level.txt
tasks_library-0.1.0.dist-info/RECORD
